wuFoil/__init__.py
wuFoil/airfoil.py
wuFoil/analysis.py
wuFoil/base.cfg
wuFoil/flight_conditions.py
wuFoil/meshing.py
wuFoil/parallel_computing.py
wuFoil/runner.py
wufoil-0.1.0.dist-info/licenses/LICENSE
wufoil-0.1.0.dist-info/METADATA
wufoil-0.1.0.dist-info/WHEEL
wufoil-0.1.0.dist-info/top_level.txt
wufoil-0.1.0.dist-info/RECORD
