Metadata-Version: 2.4
Name: wuFoil
Version: 0.1.0
Summary: An all in one airfoil modelling, meshing, analysis, and optimization tool with built in support for gmsh, SU2, and xfoil
Author-email: Mike Kiely <k.mike@wustl.edu>
License-Expression: GPL-3.0-or-later
Requires-Python: >=3.7
License-File: LICENSE
Requires-Dist: numpy
Requires-Dist: scipy
Requires-Dist: matplotlib
Requires-Dist: pandas
Requires-Dist: gmsh
Provides-Extra: lite
Requires-Dist: numpy; extra == "lite"
Requires-Dist: scipy; extra == "lite"
Requires-Dist: matplotlib; extra == "lite"
Requires-Dist: pandas; extra == "lite"
Dynamic: license-file
